{
    "doc_class": "1",
    "doc_id": "부산지방법원-2015가단77911",
    "casenames": "대여금등",
    "normalized_court": "부산지방법원",
    "casetype": "civil",
    "sentences": [
        "다음 사실은 당사자 사이에 다툼이 없거나 갑 제2~10, <삭제>증(가지번호 포함, 이하 같음)의 각 기재에 변론 전체의 취지를 종합하여 인정할 수 있다.\n",
        "가. 원고는 2001. 12. 1.경부터 2006. 6. 경까지 C 주식회사(이하 'C'이라고만 하고, 다른 회사들도 처음에만 그 상호를 완전히 표시한 다음 이후로는 '주식회사'의 표시를 생략하기로 한다)에서 상무이사로 근무한 자이고, 피고는 D 주식회사의 경영주(대표이사)였던 자이다.\n",
        "나. C은 2004. 8. 18.경 <삭제> 사이에 청주시 상당구 공사를 대금 543억 4천만 원(부가가치세 포함), 기간 2004. 9. 1.부터 2006. 4. 30.까지로 정하여 도급 받기로 하는 계약을 체결한 후, 2004. 11. 11. D과 사이에 D이 외자를 유치하여 C에 130억 원이 대출되도록 하여 주고 그 대가로 C D 에 외자유치비용과 수수료를 지급하기로 하는 내용의 계약(이하 '이 사건 계약'이라 한다)을 체결하고, 같은 날 D에 외자유치업무 추진비용으로 1,500만 원을 지급하였다.\n",
        "다. 원고는 2005. 2. 17.경부터 2005. 5.31. 경까지 사이에 D 에 2억 1,410만 원(= 2,500만 원 + 5,000만 원 + 1,700만 원 + 2,000만 원 + 5,000만 원 + 4,500만 원 + 480만 원 + 230만원)을 송금하고, 현금 등으로 2,100만 원을 지급하여, 그 지급액이 합계 2억 3,500만 원이 된 것으로 보인다.\n",
        "라. 피고는 2005. 5. 31. 원고에게 아래와 같은 내용의 '차용영수증'(이하 '이 사건 차용증'이라 한다)을 작성해 주고, 이에 관한 담보 명목으로 충남 금산군 F 임야에 관하여 매도인 피고, 매수인 원고, 대금 1억 5,000만 원으로 된 매매계약서(이하 '이 사건 매매계약서'라 한다)도 작성해 주었다.\n",
        "마. 한편, 피고와 D 2005. 5. 20. C의 채권자인 <삭제> 사이에 C의 I에 대한 채무액 1억 원을 연대보증하기로 하는 약정을 맺었고, D은 같은 날 I에 액면 1억 원의 약속어음을 발행하여 주었다.\n",
        "바. 피고는 2007. 8. 30. 원고에게 아래와 같은 내용의 지불각서(이하 '이 사건 지불각서'라 한다)를 작성해 주었다.\n",
        "피고는 C을 대신한 원고로부터 외자유치비용 등으로 합계 2억 3,500만 원을 지급받고, 2005. 5. 31. 원고에게 이 사건 차용증을 작성해 준 뒤, C을 대위하여 1에 변제한 1억 원을 공제한 나머지 1억 3,500만 원에 관하여 2007. 8. 30. 원고에게 이 사건 지불각서를 작성해 주었으므로, 이 사건 지불각서에 따라 원고에게 1억 3,500만 원 및 그에 대한 지연손해금을 지급할 의무가 있다.\n",
        "원고는 2004. 11. 11. C D 사이에 이 사건 계약이 체결되도록 주도한 후, C이 발행한 어음을 할인하여 D에 2억 1,400만 원을 외자유치비용 명목으로 송금해 주었는데, C로부터 어음할인의 방법으로 차용한 4억 3,000만 원의 변제를 독촉받게 되자, C로부터 위 차용금에 관한 소송을 당하지 않고 C의 대표이사인 J과 경영주인 KJ의 형으로부터 지원을 받기 위하여 피고에게 단지 J 등에 대하여 보여주는 용도로만 사용하겠다는 취지로 말하고 이를 그대로 믿은 피고로부터 이 사건 차용증과 매매계약서 및 지불각서를 작성 · 교부받았는데, C이 도산하여 청산 종결되고 나자, 이 사건 차용증과 매매계약서 및 지불각서를 악용하여 허위의 주장으로 이 사건 소를 제기한 것이다.\n",
        "위 인정사실에 의하면, 피고는 이 사건 지불각서의 내용과 같이 원고에게 1억 3,500만 원을 2012. 8. 30.까지 변제하기로 약정한 것으로 추정되므로, 특별한 사정이 없는 한 원고에게 이를 변제할 의무가 있다.\n",
        "원고가 C로부터 자신의 차용금 채무에 관한 소송을 당하지 않고 C의 대표이사인 J과 경영주인 K으로부터 지원을 받기 위하여 피고에게 단지 J 등에 대하여 보여주는 용도로만 사용하겠다는 취지로 말하고 이를 그대로 믿은 피고로부터 이 사건 차용증과 매매계약서 및 지불각서를 작성・교부받은 것인지 여부에 관하여 보건대, 갑 제11~14호증의 각 기재에 비추어 피고가 제출한 증거만으로는 이를 인정하기에 부족하고, 달리 이를 인정할 만한 자료가 없으므로, 피고의 주장은 받아들이기 어렵다.\n"
    ],
    "announce_date": "2016-06-23T09:00:00.000+09:00"
}