{
    "doc_class": "1",
    "doc_id": "서울중앙지방법원-2023나24908",
    "casenames": "구상금",
    "normalized_court": "서울중앙지방법원",
    "casetype": "civil",
    "sentences": [
        "가. 2022. 7. 9. 11:14경 안산시 단원구 고잔동 부근 도로에서 원고 피보험 차량(차량번호 1 생략)과 피고 피보험 차량(차량번호 2 생략) 사이에서 교통사고가 발생하였다(이하 ‘원고 차량’, ‘피고 차량’이라 한다).\n",
        "나. 원고는 2022. 7. 14. 원고 차량 수리비로 자기부담금 404,000원을 제외한 1,620,000원을 보험금으로 지급하였다.\n",
        "위 사고는 원고 차량이 4차로에서 3차로로 진로를 변경하면서, 3차로에서 정상 주행 중인 피고 차량을 충격하여 발생하였다.  사고 당시 원고 차량 운전자가 방향지시등을 켜지도 않은 채 차로를 변경한 점(갑4), 진로를 변경하려는 경우 그 변경하려는 방향으로 오고 있는 다른 차의 정상적인 통행에 장애를 줄 우려가 있을 때에는 진로를 변경하여서는 아니 됨에도 원고 차량 운전자가 이를 소홀히 한 점, 원고 차량의 왼쪽 앞부분으로 피고 차량의 오른쪽 측면을 충격한 사고인 점(갑3), 피고 차량 운전자에게 사고를 예견하거나 회피할 가능성이 있었다고 보이지 않는 점 등을 종합해 볼 때, 원고 차량 운전자의 과실이 100%라고 봄이 타당하다.\n"
    ],
    "announce_date": "2023-09-22T09:00:00.000+09:00"
}