{
    "doc_class": "1",
    "doc_id": "서울중앙지방법원-2016가단5195448",
    "casenames": "구상금",
    "normalized_court": "서울중앙지방법원",
    "casetype": "civil",
    "sentences": [
        "1. 원고의 청구를 기각한다.",
        "2. 소송비용은 원고가 부담한다.",
        "피고는 원고에게 47,414,743원 및 이에 대하여 2015. 8. 12.부터 이 사건 소장 부본 송달일까지 연 5%, 그 다음날부터 다 갚는 날까지 연 15%의 각 비율로 계산한 금원을 지급하라.",
        "1. 기초사실\n",
        "가. 원고는 2014. 8. 21.경 A과 사이에, 보험목적물을 대구 달서구 B 소재 건물 중 3층과 그곳에서 A이 운영하는 'C'이라는 상호의 체육도장(이하, '이 사건 체육도장'이라고 한다)에 비치된 시설 및 집기, 비품 등으로 정하고 화재로 인하여 위 보험목적물에 발생하는 손해를 보상하기로 하는 화재보험계약을 체결한 보험자이다.\n",
        "나. 피고는 2010. 2. 3.경 선풍기 등의 제조 및 판매를 사업목적으로 하여 설립된 회사이다.\n",
        "다. 2015. 7. 4. 02:10경 이 사건 체육도장 내부에서 발화하여 그곳에 있던 선풍기(모델명 HVF-3000, 이하, '이 사건 선풍기'라고 한다)와 집기, 내부시설, 건물 일부 등을 태우는 화재가 발생하였다(이하, '이 사건 화재'라고 한다).\n",
        "라. 국립과학수사연구원은 화재현장에서 수거한 이 사건 선풍기를 감정한 결과, 이 사건 화재는 \"이 사건 선풍기의 내부 모터 권선의 절연이 손상되는 과정에서 발생되는 전기적인 발열에 의하여 발화된 것으로 추정 가능하다\"는 결론을 내렸다.\n",
        "마. 원고는 2015. 8. 11. 이 사건 화재로 인한 손해의 보상으로 보험금 47,414,743원을 지급하였다.\n",
        "[인정근거] 갑 제1 내지 <삭제>증, 갑 제7 내지 <삭제>증, 갑 제13호증의 각 기재, 변론 전체의 취지\n",
        "2. 당사자의 주장 및 판단\n",
        "가. 당사자의 주장 요지\n",
        "원고는, 피고가 이 사건 선풍기의 제조업자임을 전제로, 이 사건 화재는 이 사건 선풍기의 제조상 결함으로 발생한 것이므로, 피고는 제조물책임의 법리에 따라 피해자를 대위하는 원고에게 지급보험금 47,414,743원 상당의 손해를 배상할 책임이 있다고 주장한다. \n",
        "이에 대하여 피고는, 이 사건 선풍기를 제조한 사실이 없다고 주장한다.\n",
        "나. 판단\n",
        "1) 먼저 피고가 이 사건 선풍기를 제조하였는지에 관하여 보건대, 피고가 2010. 2. 3.경 선풍기 등의 제조 및 판매를 사업목적으로 하여 설립된 회사인 사실은 앞서 인정한 바와 같다. 그런데 갑 제5호증, 갑 제12, <삭제>증의 기재 및 갑 제14호증의 영상, 이 법원의 한국기계전기전자시험연구원에 대한 사실조회회보에 변론 전체의 취지를 종합하면, 이 사건 선풍기는 한빛전자㈜를 제조자로 표시한 OEM 방식으로 제조된 제품인 사실, 이 사건 선풍기의 제품표시서에는 \"안전인증번호 HH07142-2007B\", \"모델명 HVF-3000\", \"제조년월일 2008년 4월\"로 표시되어 있는 사실, 나아가 이 사건 선풍기는, 1999. 8. 30.경 전자부품 제조 및 판매업 등을 사업목적으로 설립된 주식회사 신지남(변경 전 상호 주식회사 신흥)이 2002. 3. 20. 안전인증번호 HH07142-2007A로 인증받은 기본모델명 \"SGN-1F-302\"의 파생모델인 사실, 이후 기본모델명 \"SGN-1F-302\"의 선풍기는 파생모델의 추가, 변경, 제조업자의 상호변경 등에 따라 인증번호가 2003. 3. 4. \"HH07142-2007B\", 2005. 9. 23. HH07142-2007C, 2007. 5. 29. HH07142-2007D로 순차 변경된 사실, 그중 2003. 3. 4. 인증번호 \"HH07142-2007B\"로 인증받은 파생모델은 SIF-302FAS, LGT-G75ES, LGT-G753ES, SGN-IF303 제품이었던 사실, 피고는 2011. 4. 5. 제조업자를 <삭제> 피고로 변경하고 \"HVF-3000\"의 선풍기를 파생모델로 추가하여 인증번호 \"HH07142-2007F\"의 전기용품안전인증서를 발급받은 받은 사실 등이 인정되는바, 위 인정사실을 종합하여 보면, 이 사건 선풍기는 피고 회사가 설립되기 이전인 2008. 4.경 피고와는 다른 법인격을 가진 <삭제> 파생모델 \"HVF-3000\"에 대한 안전인증을 받지 않고 제조한 제품으로 추단될 뿐이고, 달리 피고가 이 사건 선풍기를 제조하였다고 인정할 증거가 없으므로, 피고가 이 사건 선풍기의 제조업자임을 전제로 하는 원고의 위 주장은 이유 없다.\n",
        "2) 이에 대하여 원고는, 피고가 <삭제> 이 사건 선풍기에 대한 제조업자로서의 권리, 의무 등을 승계한 것이라고 주장한다.\n",
        "살피건대, 피고가 2011. 4. 5. 제조업자를 <삭제> 피고로 변경하고, 파생모델에 HVF-3000를 추가하여 인증번호 HH07142-2007F로 전기용품안전인증서를 발급받은 받은 사실은 앞서 본 바와 같고, 나아가 피고와 <삭제> 상호의 주요 부분인 \"신지남\"이 공통된 점 등은 인정되나, 그러한 사정만으로는 피고가 <삭제> 이 사건 선풍기에 대한 제조물책임을 승계하였다고 볼 수 없고, 달리 이를 인정할 증거가 없으므로, 원고의 위 주장은 이유 없다.\n",
        "3. 결론\n",
        "그렇다면, 원고의 청구는 이유 없으므로 이를 기각하기로 하여 주문과 같이 판결한다.\n"
    ],
    "announce_date": "2017-09-15T09:00:00.000+09:00"
}