{
    "doc_class": "1",
    "doc_id": "부산지방법원-2017가단319060",
    "casenames": "손해배상(기)",
    "normalized_court": "부산지방법원",
    "casetype": "civil",
    "sentences": [
        "1. 피고는 원고에게 39,359,536원 및 이에 대하여 2016. 11. 15.부터 2017. 6. 16.까지 연 5%, 그 다음날부터 다 갚는 날까지 연 15%의 각 비율로 계산한 돈을 지급하라.",
        "2. 소송비용은 피고가 부담한다.",
        "3. 제1항은 가집행할 수 있다.",
        "주문과 같다.",
        "1. 사실관계\n",
        "가. 원고는 생활정보지에서 배달사원 모집 광고를 보고 성명불상자에게 연락하여 현금배송 업무를 하기로 하면서 일당을 수령하기 위한 용도로 평소 이용하고 있던 원고 명의의 우체국계좌(B) 및 농협계좌(C)를 알려주었다.\n",
        "원고는 아래와 같이 원고의 계좌로 총 14회 입금된 돈 합계 175,398,000원을 입금된 즉시 전부 인출하여 성명불상자에게 전달하였다.\n",
        "<이미지1>\n",
        "나. 그 후 피해자의 신고로 원고의 계좌가 보이스피싱 범죄에 이용되었음이 밝혀져 위 계좌는 전부 지급정지되었고, 피고는 2016. 9. 2. 원고의 우체국계좌 잔액 32,611,685원 및 농협계좌 잔액 6,747,847원에 대하여 전기통신금융사기 피해 방지 및 피해금 환급에 관한 특별법에 따른 채권소멸절차개시를 공고함과 동시에 원고에게 채권소멸절차개시를 통지하고 이에 대한 이의가 있는 때에는 공고일로부터 2개월이 경과하기 전까지 이의신청을 해야한다는 점을 알려주었다. 원고는 위 기간 내에 이의를 신청하지 않았고, 피고는 이의기간 종료 후 2016. 11. 3. 원고의 위 각 계좌 예금채권이 소멸되었음을 공고하고, 금융기관을 통해 피해구제를 신청한 피해자들에게 2016. 11. 14. 원고의 우체국계좌에서 32,611,681원, 2016. 11. 15. 원고의 농협계좌에서 6,747,855원을 피해환급금으로 지급하였다.\n",
        "다. 원고는 전자금융거래의 접근매체를 양도하였다는 범죄사실로 2016. 12. 22. 부산지방검찰청(2016형제94178호) 및 2017. 4. 28. 대구지방검찰청(2017형제2455호)으로부터 각 전자금융거래법위반으로 기소유예처분을 받았고, 이에 대하여 각 헌법소원심판청구를 하여 부산지방검찰청 기소유예처분에 관하여는 2017헌마137호로 2017. 5. 25., 대구지방검찰청 기소유예처분에 관하여는 2017헌마555호로 2017. 9. 28. '계좌번호는 전자금융거래법이 양도를 금지하는 접근매체에 해당하지 않을 뿐만 아니라 계좌번호를 알려주는 행위만으로는 소유권 내지 처분권이 확정적으로 이전된다고 볼 수 없어 위 법이 금지하는 \"양도\"에 해당한다고 볼 수 없으므로, 위 기소유예처분은 수사미진 및 법리오해에 의한 것으로 원고의 평등권과 행복추구권을 침해하므로 이를 취소한다'는 헌법재판소의 결정을 받았다. 이에 따라 부산지방검찰청(2017년 형제33123호)은 2017. 6. 20., 대구지방검찰청(2017년 형제54486호)은 2017. 10. 25. 원고의 전자금융거래법위반에 대해 전부 혐의없음 처분을 하였다.\n",
        "또한 원고는 보이스피싱에 의한 사기범행을 알면서 현금을 인출하여 건네줌으로써 범행을 용이하게 하였다는 사기방조 혐의에 관해서 2017. 1. 31. 부산지방검찰청으로부터 혐의없음 처분을 받았다.\n",
        "[인정 근거] 갑 <삭제>증부터 갑 <삭제>증, 을 <삭제>증의 1부터 을 <삭제>증의 11의 각 기재, 변론 전체의 취지\n",
        "2. 관련 법령\n",
        "(1) 전기통신금융사기 피해 방지 및 피해금 환급에 관한 특별법(이하 '특별법'이라고 한다)\n",
        "<이미지2>\n",
        "<이미지3>\n",
        "<이미지4>\n",
        "나. 전기통신금융사기 피해 방지 및 피해금 환급에 관한 특별법 시행령\n",
        "<이미지5>\n",
        "3. 원고의 청구원인에 관한 판단\n",
        "가. 원고의 주장\n",
        "원고는 위 우체국계좌 및 농협계좌의 소멸된 예금채권은 특별법이 정한 전기통신금융사기로 인한 피해금에 해당하지 않는다고 주장하며, 피고에 대하여 특별법 제13조에 따라 소멸된 채권의 환급을 청구한다.\n",
        "나. 판단\n",
        "1) 법률 요건에 해당하는지 여부\n",
        "특별법 제13조에 의하면, 소멸채권 환급이 인정되기 위해서는 소멸된 채권이 전기통신금융사기로 인한 피해금에 해당하지 않고, 원고가 특별법이 정한 기간 내에 이의제기를 하지 못한 정당한 사유가 있어야 하므로, 위 요건이 인정되는지 살펴본다.\n",
        "(가) 소멸된 원고의 예금채권이 피해금에 해당하는지 여부\n",
        "특별법 제2조에 의하면, \"피해금\"이란 전기통신금융사기로 인하여 피해자의 계좌에서 사기이용계좌로 송금·이체된 금전을 의미하는데, 앞에서 인정한 사실에 의하면 원고의 계좌를 이용한 성명불상자의 전기통신금융사기로 인하여 피해자들의 계좌에서 원고의 계좌로 송금된 돈 합계 175,398,000원은 전부 인출되어 성명불상자에게 지급된 사실이 인정되므로, 그 이후 지급정지되어 채권소멸절차가 진행된 원고의 우체국계좌 잔액 32,611,685원 및 농협계좌 잔액 6,747,847원은 전기통신금융사기로 인하여 피해자의 계좌에서 송금된 금전이 아님이 분명하다.\n",
        "피고는 불특정성을 가지는 금전의 성격상, 사기이용계좌에 남아있는 금전은 원고 소유의 기존 금전과 구별되지 않고 그 일체가 특별법이 정한 피해금에 해당한다고 주장하나, 이는 법률의 명문 규정에 반하는 해석으로 받아들이지 않는다.\n",
        "(나) 이의제기를 하지 못한 정당한 사유가 인정되는지 여부\n",
        "특별법 제7조에 의하면 이의제기를 하려는 자는 '해당 계좌가 사기이용계좌가 아니라는 사실을 소명'하여야 하고, 시행령 제7조에 의하면 '사기이용계좌가 아니라는 사실을 증명하는 자료'를 첨부하여야 하는데, 특별법 제2조에 의하면 사기이용계좌란 피해자의 자금이 송금·이체된 계좌 및 해당 계좌로부터 자금의 이전에 이용된 계좌를 말한다.\n",
        "앞에서 인정한 사실에 의하면, 원고의 우체국계좌 및 농협계좌는 성명불상자의 전기통신금융사기로 인하여 피해자의 자금이 송금된 사기이용계좌에 해당하므로 원고로서는 위 계좌가 사기이용계좌가 아니라는 사실을 소명하거나 이를 증명하는 자료를 첨부하여 이의하는 것이 처음부터 불가능하였다고 보이고, 원고는 전자금융거래법위반으로 기소유예처분을 받았다가 이에 대한 헌법소원심판을 청구하여 기소유예처분 취소결정을 받음으로써 결국 전자금융거래법위반에 관하여 혐의없음 처분을 받았고, 사기방조에 관해서도 협의없음 처분을 받았는데, 이러한 모든 결정은 이의기간이 종료된 이후에서야 이루어졌으므로 원고로서는 소멸된 채권이 피해금에 해당하지 않는다는 사실에 관해서도 이의 기간 내에 소명하거나 관련 증명자료를 제출하기 어려웠다고 보인다. \n",
        "이러한 사정을 고려하면, 원고로서는 이의기간 내에 이의를 하지 못한 정당한 사유가 있었다고 인정된다.\n",
        "2) 피고의 주장에 관한 판단\n",
        "피고는, 원고에 대한 채권환급을 인정하는 경우 피해환급금을 지급한 금융기관은 피해자들로부터 이를 부당이득으로 반환받아야 하고 그렇다면 피해자들은 원고에게 손해배상을 청구하는 등 무의미한 절차가 반복될 뿐이므로, 원고의 청구를 인정하는 것은 피해자의 신속구제를 위한 특별법의 제정 취지에 반한다고 주장한다.\n",
        "그러나, 원고에게 소멸된 채권을 환급하더라도 금융기관이 피해자들로부터 부당이득 반환을 청구할 수 있을 것인지는 불분명할 뿐 아니라, 전기통신금융사기로 인한 피해금이 아닌 금전에 대하여도 명의인의 예금채권을 소멸시켜 피해자들에게 피해환급금을 지급하고자 하는 것이 위 특별법의 제정 취지는 아니라고 보인다. \n",
        "피고의 주장은 이유없다.\n",
        "다. 소결\n",
        "원고는 특별법 제13조 제1항 각 호에서 정한 소멸채권의 환급을 청구할 수 있는 요건을 모두 갖추었다고 보이므로, 피고는 원고에게 특별법에 따른 채권소멸절차로 인해 소멸되어 피해자들에게 환급된 금액 합계 39,359,536원(우체국계좌 32,611,681원 + 농협계좌 6,747,855원) 및 이에 대하여 채권소멸일 이후로서 원고가 구하는 2016. 11. 15.부터 이 사건 소장 부본 송달일임이 기록상 분명한 2017. 6. 16.까지 민법이 정한 연 5%, 그 다음날부터 다 갚는 날까지 소송촉진 등에 관한 특례법이 정한 연 15%의 각 비율로 계산한 지연손해금을 지급할 의무가 있다.\n",
        "4. 결론\n",
        "원고의 청구는 전부 이유 있으므로 이를 인용한다.\n"
    ],
    "announce_date": "2018-01-31T00:00:00.000+09:00"
}