{
    "doc_class": "1",
    "doc_id": "대구지방법원-2019가합200724",
    "casenames": "대여금",
    "normalized_court": "대구지방법원",
    "casetype": "civil",
    "sentences": [
        "1. 원고들의 청구를 모두 기각한다.",
        "2. 소송비용은 원고들이 부담한다.",
        "피고는, 1. 원고 A에게 654,925,941원 및 그 중 644,925,941원에 대하여는 이 사건 소장 부본 송달일 다음날부터 2019. 5. 31.까지는 연 15%의, 그 다음날부터 다 갚는 날까지는 연 12%의 각 비율로 계산한 돈을, 10,000,000원에 대하여는 이 사건 청구취지 및 청구원인 변경신청서 부본 송달일 다음날부터 다 갚는 날까지 연 12%의 비율로 계산한 돈을, 2. 원고 B에게 212,110,604원 및 그 중 206,110,604원에 대하여는 이 사건 소장 부본 송달일 다음날부터 2019. 5. 31.까지는 연 15%의, 그 다음날부터 다 갚는 날까지는 연 12%의 각 비율로 계산한 돈을, 6,000,000원에 대하여는 이 사건 청구취지 및 청구원인 변경신청서 부본 송달일 다음날부터 다 갚는 날까지 연 12%의 비율로 계산한 돈을 각 지급하라.",
        "1. 기초사실\n",
        "가. 당사자들의 지위\n",
        "피고 회사는 풍력발전사업을 영위하는 회사이고, 피고 회사의 실질적인 소유자 및 경영자인 D에 대하여 원고 A는 매제, 원고 B는 자녀로서, 원고들은 위 회사의 명의상 주주였다가 그 주식을 주식회사 E(이하 'E'라 한다)에 양도한 사람들이다.\n",
        "나. D의 이 사건 사업의 추진\n",
        "D는 F <삭제> 피고 회사를 실질적으로 운영하면서 2008. 10.경부터 청송군 G, H 일대에 총 사업비 약 2,000억 원을 들여 풍력발전소를 건설하는 풍력발전단지 개발사업(이하 '이 사건 사업'이라 한다)을 추진하였다.\n",
        "다. 이 사건 사업권 등의 양도\n",
        "1) D는 2016. 4. 29. 이 사건 사업권 일체를 E에 양도하면서 계약 당사자를 F <삭제> 피고 회사와 E로 하는 양도계약서(이하 위 계약을 '이 사건 양수도 계약'이라 한다)를 작성하였는데, 그 주요 내용은 다음과 같다.\n",
        "<이미지2-0>\n",
        "<이미지3-0>\n",
        "2) 같은 날, 원고들을 비롯한 피고 회사의 주주 전원은 E와 사이에 발행 주식 총 30,000주 가운데 27,000주(나머지 3,000주는 원고 B가 보유)를 E에 양도하는 내용의 계약을 체결하면서 '대금은 66억 원으로 하고, 그 중 15억 원은 계약 체결일로부터 10영업일 이내에, 18억 원은 2016. 7. 8.까지, 나머지 33억 원은 2단계 풍력발전사업(풍력터빈 10기 추가설치)이 관계당국에 의해 최종허가 되고 2단계 사업비 금융조달이 완료된 때 지급한다'고 정하였다.\n",
        "라. 이 사건 사업의 진행 상태\n",
        "1) 피고 회사는 이 사건 사업 1단계로 풍력터빈 10기에 대한 청송군의 관리처분계획 입안 결정을 받고 대구환경청의 환경영향평가 협의를 완료하는 등 관계당국의 허가를 받았고, E는 D에게 주식양수대금 중 33억 원을 지급하였다.\n",
        "2) 이후 피고 회사는 2단계 사업 일환으로 풍력터빈 14기를 추가하여 대구환경청에 환경영향평가를 제출하였으나 환경영향평가서가 부동의 되었고, 이후 주민 반대 등으로 인하여 위 14기에 대한 허가가 이루어지지 않고 있다.\n",
        "마. 이 사건 금원의 지급\n",
        "한편, 피고 회사에, 원고 A는 2016. 5. 19. 부터 2016. 10. 10. 까지 합계 1,145,000,000원을, 원고 B는 2016. 5. 13. 부터 2017. 4. 19. 까지 합계 896,700,000원(이하 원고들이 지급한 금원을 '이 사건 금원'이라 한다)을 각 지급하였다.\n",
        "[인정 근거] 다툼 없는 사실, 갑 제1, <삭제>증(가지번호 있는 것은 각 가지번호 포함, 이하 같다), 을 제1, 2, <삭제>증의 각 기재, 변론 전체의 취지\n",
        "2. 당사자들 주장의 요지\n",
        "가. 원고들의 주장\n",
        "1) 원고들은 이 사건 금원을 피고 회사에 지급함으로써 이를 대여하였다. \n",
        "위 대여금 채권은 이행기의 정함이 없는 채권인데, 원고들이 이 사건 소로써 이행을 청구하여, 이행기가 모두 도래하였다. \n",
        "한편, 원고들은 이 사건 양수도 계약 당시 874,663,454원을 향후 대여금 반환 시 차감하기로 약정하였다. \n",
        "따라서 피고는 이 사건 금원에서 874,663,454원을 각 대여금액에 따라 안분하여 공제한 후 차액으로, 원고 A에게 654,925,941원, 원고 B에게 212,110,604원(원고 B의 경우 제3자에게 위 채권 중 3억 원을 양도하였으므로 이 금액도 추가공제) 및 각 이에 대한 지연손해금을 지급할 의무가 있다.\n",
        "2) 가사 원고들의 대여금 청구에 이 사건 양수도 계약의 변제기 조항이 적용된다고 하더라도, 그 변제기는 '2단계 사업을 위한 금융조달 완료시'인데, 피고 회사가 2단계 사업을 포기하고 중단한 상태여서 금융조달이 불가능한 것으로 확정되었으므로 그 이행기가 도래하였다고 보아야 한다.\n",
        "나. 피고의 주장\n",
        "1) 이 사건 양수도 계약서는 피고 회사의 주식 및 경영권 등을 양도하는 내용이므로 그 기재에도 불구하고 그 당사자는 실 소유자 및 경영자인 D이다. \n",
        "따라서 D가 원고들을 통하여 피고 회사에 이 사건 금원을 입금한 것은 대여금이 아니라 이 사건 양수도 계약서 제4조 제1항 및 부속합의서 #1 제2조 따라 D가 피고 회사의 미지급금 및 채무를 선지급해야 할 의무를 이행한 것이다. \n",
        "그러므로 원고들의 이 사건 청구는 대여금 반환청구가 아니라 정산금 지급청구에 해당한다.\n",
        "2) 위 계약서 조항에 따르면 E의 정산금 지급의무의 이행기는 '2단계 금융조달 완료시 '인데 아직 금융조달이 미완료 상태이므로 이행기가 도래하지 않았고, 피고 회사가 2단계 사업을 포기하고 중단한 것도 아니므로 금융조달이 불가능한 것으로 확정되지도 않았다.\n",
        "3) 가사 피고 회사의 정산금 지급의무가 인정된다고 하더라도, 부속합의서 #1의 [첨부1]에 명시된 항목에 대하여만 정산하기로 약정하였는데(부속합의서 #1 제2조), 이 사건 청구금액 중 374,000,000원은 위 항목에서 예정한 자금 집행이 아니므로 정산 대상에서 공제되어야 하고, 297,664,210원을 2단계 사업권 및 주식양도대금 선급금 명목으로 이미 입금하였으므로 정산 대상에서 차감하여야 한다.\n",
        "3. 판단\n",
        "가. 이 사건 금원이 피고 회사에 대한 대여금인지 여부\n",
        "1) 앞서 든 증거들과 갑 제5호증의 기재 및 변론 전체의 취지에 의하면 다음과 같은 사정을 인정할 수 있다.\n",
        "① 이 사건 양수도 계약은 그 계약서(을 제1호증)에 기재된 당사자 '갑'이 F <삭제> 피고 회사이나, 그 계약 내용은 갑이 보유하는 피고 회사의 주식 및 경영권을 양도하고 주식양도 대금을 수령하는 내용이고, 위 양수도 계약과 같은 날 명의상 주주들인 원고들을 비롯한 주주 전원이 위 계약 내용과 동일하게 주식을 E에 양도하기로 하는 주식양수도계약서(을 제2호증)를 작성하기도 한 점에 비추어 볼 때 이 사건 양수도 계약의 실질적인 당사자는 그 기재에도 불구하고 피고 회사의 실 소유자 및 경영자로서 이 사건 사업권을 양도한 D라고 볼 수 있다. \n",
        "② 한편, 이 사건 양수도 계약에서 피고 회사의 미지급금 및 채무에 대해서 갑의 자체비용으로 선지급하고, 해당 비용은 2단계 사업을 위한 금융조달 완료 후 정산하여 을이 갑에게 지급하기로 약정하였으므로(계약서 제4조 제1항, 부속합의서 #1 제2조), D는 피고 회사의 위 미지급금 및 채무를 선지급할 의무를 부담하고 있었다. \n",
        "③ 따라서 D 및 원고들이 이 사건 금원을 피고 회사에 입금하고, 피고 회사가 위 금원을 자신의 채무를 변제하는 등 용도로 사용한 점에 비추어 볼 때 이 사건 금원 지급은 D가 위 양수도 계약에 따라 피고 회사의 미지급금 및 채무를 선지급하여야 할 의무를 이행하기 위한 것으로 판단된다. \n",
        "④ 원고들은 E로부터 주식양수도대금 중 이미 지급받은 33억 원 가운데 일부로써 이 사건 금원을 재차 피고 회사에 대여하였다고 주장하나, 그 금원이 22억 원에 이를 정도로 상당히 거액임에도 별도로 대여계약서를 작성하거나 담보를 설정해 두지 않았고, 이 사건 양수도 계약에 따른 의무 이행이 아니라면 원고들이 위와 같이 대여금을 지급할 특별한 이유도 찾아볼 수 없다. \n",
        "⑤ 원고도 이 사건 금원에서 이 사건 양수도 계약 당시 차감하기로 약정한 874,663,454원을 뺀 나머지 돈을 청구하는 것으로 보아 원고 스스로 이 사건 청구가 이 사건 양수도 계약을 근거로 한 청구임을 자인하고 있다.\n",
        "2) 이에 의하면, 원고들이 피고 회사에 이 사건 금원을 대여한 사실을 인정하기 어렵고, 달리 이를 인정할 증거가 없다. \n",
        "오히려 원고들이 지급한 위 금원은 이 사건 양수도 계약에서 예정한 대로 피고 회사의 미지급금 및 채무를 선지급할 의무를 이행한 것으로 보이므로, 위 계약에서 정한 대로 D 또는 원고들은 '2단계 사업을 위한 금융조달 완료시' 정산금을 E에 청구할 수 있을 뿐이다. \n",
        "따라서 이 사건 금원이 대여금에 해당함을 전제로 하는 원고들의 청구는 이유 없다.\n",
        "나. 정산금 채권의 변제기 도래 여부\n",
        "1) 한편 원고들의 이 사건 청구가 정산금을 청구하는 취지라고 선해한다고 하더라도, 이 사건 양수도 계약에 따른 정산의무의 주체는 E일 뿐이고, 피고 회사가 그 의무를 부담한다고 볼 만한 근거는 없다. \n",
        "원고들은 E와 이해관계를 같이 하는 피고 회사가 신의칙상 E의 의무를 공동으로 이행할 의무가 있다고 주장하나, 신의칙상 그러한 의무가 인정된다고 볼 만한 아무런 증거가 없다.\n",
        "2) 가사 피고 회사가 정산의무를 부담한다고 하더라도, 앞서 든 증거들과 을 제8, <삭제>증의 각 기재 및 변론 전체의 취지를 종합하여 인정되는 다음과 같은 사정, 즉 ① 이 사건 양수도 계약에서 정한 정산금 채권의 이행기는 '2단계 사업을 위한 금융조달 완료시'인데, 피고 회사가 약 2년 이상 2단계 사업의 인허가를 받지 못하였다거나 이렇다 할 진척을 이루어내지 못하였다는 사실만으로는 피고 회사가 2단계 사업을 포기하고 중단하여 위 금용조달이 불가능한 것으로 확정되었다고 인정하기에 부족한 점, ② D를 비롯한 원고들은 E에 대하여 이 사건 사업을 위하여 필요한 인허가 진행을 위해 개발행위허가 완료 및 통상 풍력발전사업 시행사가 행하여야 할 모든 사항의 업무를 수행하고, 사업 대상 토지의 매입 및 국유지 임대 협의와 대상 사업의 인허가 및 공사 관련한 모든 민원해결 업무를 수행할 의무를 부담하므로(이 사건 양수도 계약서 제2조 제2, 3항), 2단계 사업이 원활히 진행되지 않고 있는 데에 D 및 원고들도 책임이 있고, 특히 D가 이 사건 사업과 관련하여 청송군의회 의원에게 뇌물을 공여하는 등의 범죄사실로 2018. 8. 28. 유죄판결을 받아 위 사업 진행에 대한 반대 여론이 거세짐으로 인하여 사업 진행에 차질이 빚어지기도 한 것으로 보이는 점 등을 고려할 때, 2단계 사업을 위한 금융조달이 불가능한 것으로 확정되어 정산금 채권의 이행기가 도래하였다고 볼 수 없고, 달리 이를 인정할 증거가 없다. 따라서 어느 모로 보나 원고들의 주장은 이유 없다.\n",
        "4. 결론\n",
        "그렇다면 원고들의 이 사건 청구는 이유 없어 이를 모두 기각하기로 하여 주문과 같이 판결한다.\n"
    ],
    "announce_date": "2019-12-05T09:00:00.000+09:00"
}