{
    "doc_class": "1",
    "doc_id": "부산지방법원-2021가단310657",
    "casenames": "손해배상(기)",
    "normalized_court": "부산지방법원",
    "casetype": "civil",
    "sentences": [
        "나. 피고는 부산광역시 중구 D건물(이하 ‘이 사건 다세대주택’이라 함)을 신축하기 위해, 2012. 11. 15. 원고로부터 100,000,000원을 빌렸다.\n",
        "다. 피고는 원고를 건축주로 하여 위 다세대주택을 신축하여 2013. 5. 8. 원고의 명의로 소유권보존등기를 마쳤다.\n",
        "라. 위 다세대주택은 2014. 5. 15. E에게 2014. 5. 13.자 매매를 원인으로 하여 소유권이전등기가 이루어졌다.\n",
        "마. 위와 같은 매매로 인하여 원고에게 양도소득세가 부과되었다. 원고는 2019. 1. 18. 30,000,000원, 2019. 2. 15. 36,941,010원, 합계 66,941,010원을 양도소득세(가산금 포함)로 부산진세무서에 납부하였다.\n",
        "가. 원고는 피고에 대한 위 100,000,000원의 대여금채권을 담보하기 위해 이 사건 다세대주택의 건축주가 되었다.\n",
        "나. 피고는 원고에게 자신이 위 양도소득세를 납부하겠다고 거듭 약속을 하였음에도 이를 이행하지 않았다.\n",
        "다. 원고는 세무서에 이의제기를 하였으나 받아들여지지 않았고, 세무서로부터 계속 독촉을 받던 중, 만일 이를 납부하지 않으면 신용불량자가 되어 C의 영업을 할 수 없다는 생각에서, 위 양도소득세를 대신 납부하였다. 원고는 피고가 납부하여야 할 세금을 대위 납부한 것이다.\n",
        "라. 원고는 피고에게 속아 건축비용 100,000,000원을 빌려주었고, 피고로부터 70,000,000원의 약속어음과 30,000,000원의 현금을 받았는데, 이후 위 약속어음과 교환한 80,000,000원의 당좌수표가 부도처리 되었다. 원고는 피고에게 속아 건축주 명의를 빌려주고 피고의 양도소득세까지 대신 부담하게 되는 사기의 피해를 당했다.\n",
        "마. 그러므로 피고는 원고에게, 원고가 양도소득세로 납부한 66,941,000원 및 이에 대한 지연손해금을 지급할 의무가 있다.\n",
        "가. 갑 제3, 10 내지 <삭제>증의 각 기재만으로는 피고가 원고에게 자신이 양도소득세를 납부하겠다는 약속을 한 사실을 인정하기 부족하고, 달리 이를 인정할 증거가 없다. 원고의 주장 중 약정금으로 청구하는 주장은 받아들일 수 없다.\n",
        "나. 명의신탁자가 자신의 의사에 의해 명의신탁재산을 양도하는 경우에는 그가 양도소득을 사실상 지배, 관리, 처분할 수 있는 지위에 있다고 할 것이어서 양도소득의 납세의무자가 된다(대법원 2014. 9. 4. 선고 2012두10710 판결 참조). 과세관청이 등기명의 신탁에 따라 부동산의 공부상 소유자가 된 명의수탁자에게 양도소득세 부과처분을 하고 이에 따라 명의수탁자가 양도소득세를 납부하였더라도 명의신탁자는 여전히 과세관청에 양도소득세를 납부할 의무를 부담하고 그 의무가 소멸하는 것은 아니므로 양도소득세 납부의무를 면하는 이득을 얻게 되었다고 볼 수 없고, 따라서 명의수탁자가 명의신탁자를 상대로 양도소득세 상당의 금액에 대한 부당이득금 반환청구권을 가진다고 볼 수 없다(재산세에 관한 대법원 2020. 9. 3. 선고 2018다283773 판결의 이유<각주1> 참조). 원고의 주장에 의하면 원고는 이 사건 다세대주택에 관한 명의수탁자이고 피고는 명의신탁자로 보이는바, 위 법리에 따르면 원고가 위 다세대주택의 매매로 인한 양도소득세를 납부한 결과로 피고가 위 양도소득세 납부의무를 면하게 되는 이득을 얻었다고 볼 수 없다. 원고의 주장 중 부당이득금으로 청구하는 주장은 받아들일 수 없다.\n",
        "다. 갑 제3, 10 내지 <삭제>증의 각 기재만으로는 피고가 원고 주장의 사기를 한 사실을 인정하기 부족하고, 달리 이를 인정할 증거가 없다. 원고의 주장 중 불법행위 손해배상금으로 청구하는 주장은 받아들일 수 없다.\n"
    ],
    "announce_date": "2021-12-09T09:00:00.000+09:00"
}